featureselect/__init__.py
featureselect/base/DE.py
featureselect/base/GA.py
featureselect/base/PSO.py
featureselect/base/SA.py
featureselect/base/__init__.py
featureselect/base/utils.py
featureselect-0.0.5.dist-info/LICENSE
featureselect-0.0.5.dist-info/METADATA
featureselect-0.0.5.dist-info/WHEEL
featureselect-0.0.5.dist-info/top_level.txt
featureselect-0.0.5.dist-info/RECORD
