Metadata-Version: 2.1
Name: featureselect
Version: 0.0.5
Summary: An elegant and effectice solution to get best set of features from a numerical dataset!
Home-page: https://github.com/himanshu-dutta/featureselect
Author: Himanshu Dutta
Author-email: meet.himanshu.dutta@gmail.com
License: UNKNOWN
Keywords: featureselect
Platform: UNKNOWN
Classifier: Development Status :: 2 - Pre-Alpha
Classifier: Programming Language :: Python :: 3
Classifier: Programming Language :: Python :: 3.6
Classifier: Programming Language :: Python :: 3.7
Classifier: Programming Language :: Python :: 3.8
Classifier: License :: OSI Approved :: GNU General Public License v2 or later (GPLv2+)
Classifier: Operating System :: OS Independent
Classifier: Intended Audience :: Education
Classifier: Intended Audience :: End Users/Desktop
Requires-Dist: numpy (>=1.9.0)
Requires-Dist: scikit-learn (>=0.23.0)
